bertrand/__init__.py
bertrand/__main__.py
bertrand/bertrand.h
bertrand/common.h
bertrand/py.typed
bertrand/python.h
bertrand/regex.cpp
bertrand/regex.h
bertrand/setuptools.py
bertrand/static_str.h
bertrand/convert/__init__.py
bertrand/convert/arguments.py
bertrand/convert/base.py
bertrand/convert/boolean.py
bertrand/convert/categorical.py
bertrand/convert/complex.py
bertrand/convert/datetime.py
bertrand/convert/decimal.py
bertrand/convert/float.py
bertrand/convert/integer.py
bertrand/convert/object.py
bertrand/convert/sparse.py
bertrand/convert/string.py
bertrand/convert/timedelta.py
bertrand/decorators/__init__.py
bertrand/decorators/attachable.py
bertrand/decorators/base.py
bertrand/decorators/dispatch.py
bertrand/decorators/extension.py
bertrand/patch/__init__.py
bertrand/patch/base.py
bertrand/patch/round.py
bertrand/patch/snap.py
bertrand/patch/dt/__init__.py
bertrand/patch/dt/tz_convert.py
bertrand/patch/dt/tz_localize.py
bertrand/python/bool.h
bertrand/python/bytes.h
bertrand/python/code.h
bertrand/python/common.h
bertrand/python/complex.h
bertrand/python/datetime.h
bertrand/python/decimal.h
bertrand/python/dict.h
bertrand/python/float.h
bertrand/python/int.h
bertrand/python/list.h
bertrand/python/math.h
bertrand/python/memoryview.h
bertrand/python/range.h
bertrand/python/set.h
bertrand/python/str.h
bertrand/python/tuple.h
bertrand/python/type.h
bertrand/python/common/access.h
bertrand/python/common/control.h
bertrand/python/common/declarations.h
bertrand/python/common/except.h
bertrand/python/common/func.h
bertrand/python/common/iter.h
bertrand/python/common/object.h
bertrand/python/common/ops.h
bertrand/structs/__init__.pxd
bertrand/structs/__init__.py
bertrand/structs/linked.cpp
bertrand/structs/linked.h
bertrand/structs/linked.pyi
bertrand/structs/linked/base.h
bertrand/structs/linked/dict.h
bertrand/structs/linked/list.h
bertrand/structs/linked/set.h
bertrand/structs/linked/algorithms/add.h
bertrand/structs/linked/algorithms/append.h
bertrand-0.0.1.dist-info/LICENSE
bertrand-0.0.1.dist-info/METADATA
bertrand-0.0.1.dist-info/WHEEL
bertrand-0.0.1.dist-info/top_level.txt
bertrand-0.0.1.dist-info/RECORD
